[
    {
        "games_played": 82,
        "player_id": 2902,
        "season": 1984,
        "min": "31:00",
        "fgm": 6.11,
        "fga": 12.55,
        "fg3m": 0.06,
        "fg3a": 0.47,
        "ftm": 4.07,
        "fta": 4.72,
        "oreb": 1.27,
        "dreb": 2.05,
        "reb": 3.3,
        "ast": 8.0,
        "stl": 1.16,
        "blk": 0.22,
        "turnover": 3.75,
        "pf": 3.04,
        "pts": 16.35,
        "fg_pct": 0.487,
        "fg3_pct": 0.13,
        "ft_pct": 0.863
    },
    {
        "games_played": 76,
        "player_id": 2903,
        "season": 1984,
        "min": "29:09",
        "fgm": 3.93,
        "fga": 7.33,
        "fg3m": 0.0,
        "fg3a": 0.0,
        "ftm": 2.11,
        "fta": 2.96,
        "oreb": 2.72,
        "dreb": 5.91,
        "reb": 8.63,
        "ast": 2.83,
        "stl": 0.72,
        "blk": 2.66,
        "turnover": 2.28,
        "pf": 3.66,
        "pts": 9.97,
        "fg_pct": 0.537,
        "fg3_pct": 0,
        "ft_pct": 0.711
    },
    {
        "games_played": 75,
        "player_id": 2909,
        "season": 1984,
        "min": "18:35",
        "fgm": 2.79,
        "fga": 5.93,
        "fg3m": 0.0,
        "fg3a": 0.0,
        "ftm": 1.21,
        "fta": 2.56,
        "oreb": 1.43,
        "dreb": 2.93,
        "reb": 4.36,
        "ast": 0.52,
        "stl": 0.51,
        "blk": 0.53,
        "turnover": 1.88,
        "pf": 3.72,
        "pts": 6.79,
        "fg_pct": 0.47,
        "fg3_pct": 0,
        "ft_pct": 0.474
    },
    {
        "games_played": 62,
        "player_id": 2914,
        "season": 1984,
        "min": "19:16",
        "fgm": 3.19,
        "fga": 6.05,
        "fg3m": 0.03,
        "fg3a": 0.1,
        "ftm": 1.63,
        "fta": 2.06,
        "oreb": 1.27,
        "dreb": 2.47,
        "reb": 3.74,
        "ast": 1.29,
        "stl": 0.47,
        "blk": 1.24,
        "turnover": 1.74,
        "pf": 3.53,
        "pts": 8.05,
        "fg_pct": 0.528,
        "fg3_pct": 0.333,
        "ft_pct": 0.789
    },
    {
        "games_played": 54,
        "player_id": 2916,
        "season": 1984,
        "min": "11:57",
        "fgm": 2.04,
        "fga": 4.17,
        "fg3m": 0.02,
        "fg3a": 0.13,
        "ftm": 0.74,
        "fta": 1.33,
        "oreb": 0.37,
        "dreb": 0.93,
        "reb": 1.3,
        "ast": 1.39,
        "stl": 0.47,
        "blk": 0.02,
        "turnover": 0.92,
        "pf": 1.63,
        "pts": 4.83,
        "fg_pct": 0.489,
        "fg3_pct": 0.143,
        "ft_pct": 0.556
    },
    {
        "games_played": 82,
        "player_id": 2920,
        "season": 1984,
        "min": "37:38",
        "fgm": 9.18,
        "fga": 18.28,
        "fg3m": 0.0,
        "fg3a": 0.07,
        "ftm": 3.7,
        "fta": 5.46,
        "oreb": 2.77,
        "dreb": 7.63,
        "reb": 10.4,
        "ast": 2.73,
        "stl": 0.99,
        "blk": 2.05,
        "turnover": 3.96,
        "pf": 3.73,
        "pts": 22.06,
        "fg_pct": 0.502,
        "fg3_pct": 0.0,
        "ft_pct": 0.676
    },
    {
        "games_played": 79,
        "player_id": 2921,
        "season": 1984,
        "min": "29:00",
        "fgm": 4.13,
        "fga": 8.38,
        "fg3m": 0.09,
        "fg3a": 0.41,
        "ftm": 1.54,
        "fta": 1.78,
        "oreb": 0.48,
        "dreb": 1.66,
        "reb": 2.14,
        "ast": 7.05,
        "stl": 1.03,
        "blk": 0.11,
        "turnover": 1.9,
        "pf": 2.53,
        "pts": 9.89,
        "fg_pct": 0.492,
        "fg3_pct": 0.219,
        "ft_pct": 0.865
    },
    {
        "games_played": 78,
        "player_id": 2922,
        "season": 1984,
        "min": "18:46",
        "fgm": 2.77,
        "fga": 6.12,
        "fg3m": 0.33,
        "fg3a": 0.95,
        "ftm": 1.26,
        "fta": 1.67,
        "oreb": 0.51,
        "dreb": 1.41,
        "reb": 1.92,
        "ast": 3.12,
        "stl": 0.96,
        "blk": 0.12,
        "turnover": 1.44,
        "pf": 1.82,
        "pts": 7.13,
        "fg_pct": 0.453,
        "fg3_pct": 0.351,
        "ft_pct": 0.754
    },
    {
        "games_played": 74,
        "player_id": 2926,
        "season": 1984,
        "min": "27:18",
        "fgm": 3.93,
        "fga": 7.46,
        "fg3m": 0.0,
        "fg3a": 0.03,
        "ftm": 1.96,
        "fta": 3.0,
        "oreb": 3.11,
        "dreb": 4.54,
        "reb": 7.65,
        "ast": 1.41,
        "stl": 0.93,
        "blk": 0.93,
        "turnover": 1.81,
        "pf": 3.12,
        "pts": 9.82,
        "fg_pct": 0.527,
        "fg3_pct": 0.0,
        "ft_pct": 0.653
    },
    {
        "games_played": 82,
        "player_id": 2927,
        "season": 1984,
        "min": "30:26",
        "fgm": 4.38,
        "fga": 8.94,
        "fg3m": 0.57,
        "fg3a": 1.65,
        "ftm": 1.29,
        "fta": 1.59,
        "oreb": 0.9,
        "dreb": 1.37,
        "reb": 2.27,
        "ast": 4.26,
        "stl": 1.17,
        "blk": 0.01,
        "turnover": 1.63,
        "pf": 3.2,
        "pts": 10.62,
        "fg_pct": 0.49,
        "fg3_pct": 0.348,
        "ft_pct": 0.815
    },
    {
        "games_played": 78,
        "player_id": 2930,
        "season": 1984,
        "min": "16:08",
        "fgm": 2.51,
        "fga": 4.95,
        "fg3m": 0.13,
        "fg3a": 0.44,
        "ftm": 1.08,
        "fta": 1.28,
        "oreb": 0.24,
        "dreb": 0.63,
        "reb": 0.87,
        "ast": 2.76,
        "stl": 0.56,
        "blk": 0.04,
        "turnover": 1.03,
        "pf": 1.5,
        "pts": 6.23,
        "fg_pct": 0.508,
        "fg3_pct": 0.294,
        "ft_pct": 0.84
    },
    {
        "games_played": 82,
        "player_id": 2931,
        "season": 1984,
        "min": "38:20",
        "fgm": 10.21,
        "fga": 19.82,
        "fg3m": 0.11,
        "fg3a": 0.63,
        "ftm": 7.68,
        "fta": 9.1,
        "oreb": 2.04,
        "dreb": 4.48,
        "reb": 6.51,
        "ast": 5.87,
        "stl": 2.39,
        "blk": 0.84,
        "turnover": 3.55,
        "pf": 3.48,
        "pts": 28.21,
        "fg_pct": 0.515,
        "fg3_pct": 0.173,
        "ft_pct": 0.845
    },
    {
        "games_played": 82,
        "player_id": 2937,
        "season": 1984,
        "min": "28:38",
        "fgm": 5.21,
        "fga": 9.55,
        "fg3m": 0.01,
        "fg3a": 0.07,
        "ftm": 3.57,
        "fta": 4.88,
        "oreb": 3.24,
        "dreb": 5.33,
        "reb": 8.57,
        "ast": 1.89,
        "stl": 1.16,
        "blk": 0.98,
        "turnover": 2.54,
        "pf": 3.67,
        "pts": 14.0,
        "fg_pct": 0.545,
        "fg3_pct": 0.167,
        "ft_pct": 0.733
    },
    {
        "games_played": 81,
        "player_id": 2942,
        "season": 1984,
        "min": "29:51",
        "fgm": 4.69,
        "fga": 10.1,
        "fg3m": 0.0,
        "fg3a": 0.01,
        "ftm": 3.41,
        "fta": 4.05,
        "oreb": 2.83,
        "dreb": 4.99,
        "reb": 7.81,
        "ast": 1.95,
        "stl": 0.48,
        "blk": 1.14,
        "turnover": 1.65,
        "pf": 1.67,
        "pts": 12.79,
        "fg_pct": 0.465,
        "fg3_pct": 0.0,
        "ft_pct": 0.841
    },
    {
        "games_played": 77,
        "player_id": 2943,
        "season": 1984,
        "min": "26:54",
        "fgm": 2.68,
        "fga": 5.36,
        "fg3m": 0.0,
        "fg3a": 0.03,
        "ftm": 0.92,
        "fta": 1.35,
        "oreb": 1.95,
        "dreb": 5.95,
        "reb": 7.9,
        "ast": 1.57,
        "stl": 0.78,
        "blk": 1.35,
        "turnover": 1.75,
        "pf": 4.0,
        "pts": 6.27,
        "fg_pct": 0.499,
        "fg3_pct": 0.0,
        "ft_pct": 0.683
    },
    {
        "games_played": 77,
        "player_id": 2944,
        "season": 1984,
        "min": "31:38",
        "fgm": 4.95,
        "fga": 10.36,
        "fg3m": 0.08,
        "fg3a": 0.26,
        "ftm": 3.01,
        "fta": 3.47,
        "oreb": 0.51,
        "dreb": 1.95,
        "reb": 2.45,
        "ast": 7.75,
        "stl": 1.71,
        "blk": 0.04,
        "turnover": 2.3,
        "pf": 1.69,
        "pts": 12.99,
        "fg_pct": 0.477,
        "fg3_pct": 0.3,
        "ft_pct": 0.869
    },
    {
        "games_played": 36,
        "player_id": 2945,
        "season": 1984,
        "min": "14:26",
        "fgm": 2.33,
        "fga": 5.42,
        "fg3m": 0.03,
        "fg3a": 0.06,
        "ftm": 1.14,
        "fta": 1.39,
        "oreb": 1.08,
        "dreb": 1.36,
        "reb": 2.44,
        "ast": 0.94,
        "stl": 0.25,
        "blk": 0.19,
        "turnover": 0.94,
        "pf": 1.11,
        "pts": 5.83,
        "fg_pct": 0.431,
        "fg3_pct": 0.5,
        "ft_pct": 0.82
    },
    {
        "games_played": 55,
        "player_id": 2951,
        "season": 1984,
        "min": "30:27",
        "fgm": 7.2,
        "fga": 14.98,
        "fg3m": 0.04,
        "fg3a": 0.09,
        "ftm": 4.64,
        "fta": 5.24,
        "oreb": 1.2,
        "dreb": 2.76,
        "reb": 3.96,
        "ast": 2.45,
        "stl": 0.91,
        "blk": 0.25,
        "turnover": 2.15,
        "pf": 2.15,
        "pts": 19.07,
        "fg_pct": 0.481,
        "fg3_pct": 0.4,
        "ft_pct": 0.885
    },
    {
        "games_played": 54,
        "player_id": 2958,
        "season": 1984,
        "min": "16:58",
        "fgm": 2.15,
        "fga": 4.31,
        "fg3m": 0.0,
        "fg3a": 0.04,
        "ftm": 1.22,
        "fta": 2.26,
        "oreb": 1.59,
        "dreb": 3.26,
        "reb": 4.85,
        "ast": 0.3,
        "stl": 0.39,
        "blk": 0.3,
        "turnover": 1.19,
        "pf": 2.87,
        "pts": 5.52,
        "fg_pct": 0.498,
        "fg3_pct": 0.0,
        "ft_pct": 0.541
    },
    {
        "games_played": 72,
        "player_id": 2961,
        "season": 1984,
        "min": "34:45",
        "fgm": 8.58,
        "fga": 16.08,
        "fg3m": 0.15,
        "fg3a": 0.46,
        "ftm": 5.13,
        "fta": 5.72,
        "oreb": 1.04,
        "dreb": 2.13,
        "reb": 3.17,
        "ast": 1.47,
        "stl": 0.51,
        "blk": 0.31,
        "turnover": 1.61,
        "pf": 1.61,
        "pts": 22.44,
        "fg_pct": 0.534,
        "fg3_pct": 0.333,
        "ft_pct": 0.896
    },
    {
        "games_played": 78,
        "player_id": 2963,
        "season": 1984,
        "min": "33:32",
        "fgm": 5.41,
        "fga": 9.5,
        "fg3m": 0.08,
        "fg3a": 0.33,
        "ftm": 2.24,
        "fta": 2.55,
        "oreb": 0.69,
        "dreb": 2.09,
        "reb": 2.78,
        "ast": 6.37,
        "stl": 2.14,
        "blk": 0.31,
        "turnover": 2.03,
        "pf": 2.36,
        "pts": 13.14,
        "fg_pct": 0.57,
        "fg3_pct": 0.231,
        "ft_pct": 0.879
    },
    {
        "games_played": 75,
        "player_id": 2969,
        "season": 1984,
        "min": "21:28",
        "fgm": 2.88,
        "fga": 5.31,
        "fg3m": 0.0,
        "fg3a": 0.0,
        "ftm": 1.35,
        "fta": 1.83,
        "oreb": 1.68,
        "dreb": 3.55,
        "reb": 5.23,
        "ast": 0.68,
        "stl": 0.55,
        "blk": 0.43,
        "turnover": 1.07,
        "pf": 2.19,
        "pts": 7.11,
        "fg_pct": 0.543,
        "fg3_pct": 0,
        "ft_pct": 0.737
    },
    {
        "games_played": 79,
        "player_id": 2971,
        "season": 1984,
        "min": "26:35",
        "fgm": 6.65,
        "fga": 14.06,
        "fg3m": 0.09,
        "fg3a": 0.38,
        "ftm": 2.59,
        "fta": 3.18,
        "oreb": 0.72,
        "dreb": 1.91,
        "reb": 2.63,
        "ast": 2.42,
        "stl": 0.89,
        "blk": 0.06,
        "turnover": 1.94,
        "pf": 2.43,
        "pts": 15.97,
        "fg_pct": 0.473,
        "fg3_pct": 0.233,
        "ft_pct": 0.817
    },
    {
        "games_played": 82,
        "player_id": 2972,
        "season": 1984,
        "min": "15:40",
        "fgm": 2.29,
        "fga": 5.07,
        "fg3m": 0.05,
        "fg3a": 0.27,
        "ftm": 0.8,
        "fta": 1.1,
        "oreb": 0.26,
        "dreb": 0.95,
        "reb": 1.21,
        "ast": 2.13,
        "stl": 0.95,
        "blk": 0.2,
        "turnover": 1.21,
        "pf": 2.09,
        "pts": 5.44,
        "fg_pct": 0.452,
        "fg3_pct": 0.182,
        "ft_pct": 0.733
    },
    {
        "games_played": 70,
        "player_id": 2975,
        "season": 1984,
        "min": "25:00",
        "fgm": 2.66,
        "fga": 4.84,
        "fg3m": 0.0,
        "fg3a": 0.0,
        "ftm": 0.96,
        "fta": 1.33,
        "oreb": 1.61,
        "dreb": 4.7,
        "reb": 6.31,
        "ast": 0.74,
        "stl": 0.5,
        "blk": 2.39,
        "turnover": 1.14,
        "pf": 3.04,
        "pts": 6.27,
        "fg_pct": 0.549,
        "fg3_pct": 0,
        "ft_pct": 0.72
    },
    {
        "games_played": 52,
        "player_id": 2977,
        "season": 1984,
        "min": "7:31",
        "fgm": 0.67,
        "fga": 1.77,
        "fg3m": 0.0,
        "fg3a": 0.0,
        "ftm": 0.62,
        "fta": 0.9,
        "oreb": 0.56,
        "dreb": 1.81,
        "reb": 2.37,
        "ast": 0.29,
        "stl": 0.13,
        "blk": 0.27,
        "turnover": 0.96,
        "pf": 1.58,
        "pts": 1.96,
        "fg_pct": 0.38,
        "fg3_pct": 0,
        "ft_pct": 0.681
    },
    {
        "games_played": 77,
        "player_id": 2978,
        "season": 1984,
        "min": "23:35",
        "fgm": 3.81,
        "fga": 7.88,
        "fg3m": 0.38,
        "fg3a": 0.92,
        "ftm": 0.49,
        "fta": 0.62,
        "oreb": 0.96,
        "dreb": 1.48,
        "reb": 2.44,
        "ast": 2.58,
        "stl": 0.97,
        "blk": 0.19,
        "turnover": 0.84,
        "pf": 2.53,
        "pts": 8.48,
        "fg_pct": 0.483,
        "fg3_pct": 0.408,
        "ft_pct": 0.792
    },
    {
        "games_played": 61,
        "player_id": 2980,
        "season": 1984,
        "min": "24:58",
        "fgm": 2.49,
        "fga": 5.44,
        "fg3m": 0.0,
        "fg3a": 0.02,
        "ftm": 1.1,
        "fta": 1.54,
        "oreb": 1.77,
        "dreb": 4.59,
        "reb": 6.36,
        "ast": 1.28,
        "stl": 0.57,
        "blk": 0.34,
        "turnover": 1.05,
        "pf": 3.11,
        "pts": 6.08,
        "fg_pct": 0.458,
        "fg3_pct": 0.0,
        "ft_pct": 0.713
    },
    {
        "games_played": 80,
        "player_id": 2982,
        "season": 1984,
        "min": "35:57",
        "fgm": 6.0,
        "fga": 11.6,
        "fg3m": 0.09,
        "fg3a": 0.25,
        "ftm": 3.96,
        "fta": 5.23,
        "oreb": 1.86,
        "dreb": 3.5,
        "reb": 5.36,
        "ast": 6.79,
        "stl": 1.61,
        "blk": 0.7,
        "turnover": 3.06,
        "pf": 3.23,
        "pts": 16.05,
        "fg_pct": 0.517,
        "fg3_pct": 0.35,
        "ft_pct": 0.758
    },
    {
        "games_played": 48,
        "player_id": 2986,
        "season": 1984,
        "min": "15:25",
        "fgm": 2.25,
        "fga": 5.21,
        "fg3m": 0.0,
        "fg3a": 0.08,
        "ftm": 1.65,
        "fta": 2.04,
        "oreb": 1.5,
        "dreb": 3.63,
        "reb": 5.13,
        "ast": 0.6,
        "stl": 0.25,
        "blk": 0.23,
        "turnover": 1.42,
        "pf": 2.13,
        "pts": 6.15,
        "fg_pct": 0.432,
        "fg3_pct": 0.0,
        "ft_pct": 0.806
    },
    {
        "games_played": 79,
        "player_id": 2987,
        "season": 1984,
        "min": "34:27",
        "fgm": 9.62,
        "fga": 19.41,
        "fg3m": 0.0,
        "fg3a": 0.01,
        "ftm": 4.34,
        "fta": 5.86,
        "oreb": 3.1,
        "dreb": 5.97,
        "reb": 9.08,
        "ast": 2.89,
        "stl": 1.51,
        "blk": 0.85,
        "turnover": 2.41,
        "pf": 3.34,
        "pts": 23.58,
        "fg_pct": 0.496,
        "fg3_pct": 0.0,
        "ft_pct": 0.741
    },
    {
        "games_played": 81,
        "player_id": 2990,
        "season": 1984,
        "min": "28:27",
        "fgm": 6.68,
        "fga": 12.38,
        "fg3m": 0.32,
        "fg3a": 0.74,
        "ftm": 2.31,
        "fta": 2.81,
        "oreb": 0.7,
        "dreb": 1.89,
        "reb": 2.59,
        "ast": 3.0,
        "stl": 1.21,
        "blk": 0.21,
        "turnover": 1.67,
        "pf": 2.44,
        "pts": 15.99,
        "fg_pct": 0.539,
        "fg3_pct": 0.433,
        "ft_pct": 0.82
    },
    {
        "games_played": 80,
        "player_id": 2992,
        "season": 1984,
        "min": "33:45",
        "fgm": 7.63,
        "fga": 13.33,
        "fg3m": 0.0,
        "fg3a": 0.09,
        "ftm": 2.38,
        "fta": 3.06,
        "oreb": 2.11,
        "dreb": 4.28,
        "reb": 6.39,
        "ast": 2.51,
        "stl": 1.09,
        "blk": 0.84,
        "turnover": 2.48,
        "pf": 2.45,
        "pts": 17.63,
        "fg_pct": 0.572,
        "fg3_pct": 0.0,
        "ft_pct": 0.776
    },
    {
        "games_played": 72,
        "player_id": 2993,
        "season": 1984,
        "min": "32:51",
        "fgm": 6.33,
        "fga": 12.67,
        "fg3m": 0.1,
        "fg3a": 0.38,
        "ftm": 2.14,
        "fta": 2.69,
        "oreb": 0.56,
        "dreb": 1.69,
        "reb": 2.28,
        "ast": 6.72,
        "stl": 1.29,
        "blk": 0.11,
        "turnover": 2.52,
        "pf": 2.04,
        "pts": 14.9,
        "fg_pct": 0.5,
        "fg3_pct": 0.256,
        "ft_pct": 0.794
    },
    {
        "games_played": 77,
        "player_id": 2994,
        "season": 1984,
        "min": "36:07",
        "fgm": 6.55,
        "fga": 11.68,
        "fg3m": 0.09,
        "fg3a": 0.48,
        "ftm": 5.08,
        "fta": 6.03,
        "oreb": 1.17,
        "dreb": 5.01,
        "reb": 6.18,
        "ast": 12.58,
        "stl": 1.49,
        "blk": 0.32,
        "turnover": 3.96,
        "pf": 2.0,
        "pts": 18.26,
        "fg_pct": 0.561,
        "fg3_pct": 0.189,
        "ft_pct": 0.843
    },
    {
        "games_played": 70,
        "player_id": 2995,
        "season": 1984,
        "min": "32:24",
        "fgm": 7.1,
        "fga": 13.77,
        "fg3m": 0.0,
        "fg3a": 0.0,
        "ftm": 3.66,
        "fta": 5.5,
        "oreb": 2.7,
        "dreb": 5.11,
        "reb": 7.81,
        "ast": 2.54,
        "stl": 0.93,
        "blk": 1.33,
        "turnover": 2.96,
        "pf": 2.66,
        "pts": 17.86,
        "fg_pct": 0.516,
        "fg3_pct": 0,
        "ft_pct": 0.665
    },
    {
        "games_played": 82,
        "player_id": 2996,
        "season": 1984,
        "min": "28:15",
        "fgm": 4.23,
        "fga": 8.98,
        "fg3m": 0.11,
        "fg3a": 0.44,
        "ftm": 2.44,
        "fta": 2.98,
        "oreb": 2.3,
        "dreb": 5.07,
        "reb": 7.38,
        "ast": 1.66,
        "stl": 0.77,
        "blk": 0.76,
        "turnover": 1.2,
        "pf": 2.82,
        "pts": 11.01,
        "fg_pct": 0.471,
        "fg3_pct": 0.25,
        "ft_pct": 0.82
    },
    {
        "games_played": 21,
        "player_id": 2997,
        "season": 1984,
        "min": "16:37",
        "fgm": 3.52,
        "fga": 6.52,
        "fg3m": 0.1,
        "fg3a": 0.2,
        "ftm": 1.19,
        "fta": 1.67,
        "oreb": 1.05,
        "dreb": 0.95,
        "reb": 2.05,
        "ast": 0.67,
        "stl": 0.65,
        "blk": 0.24,
        "turnover": 0.7,
        "pf": 1.67,
        "pts": 8.33,
        "fg_pct": 0.54,
        "fg3_pct": 0.476,
        "ft_pct": 0.714
    }
]