[
    {
        "games_played": 49,
        "player_id": 1904,
        "season": 2016,
        "min": "11:24",
        "fgm": 2.22,
        "fga": 4.04,
        "fg3m": 0.0,
        "fg3a": 0.04,
        "ftm": 0.29,
        "fta": 0.45,
        "oreb": 0.84,
        "dreb": 2.06,
        "reb": 2.9,
        "ast": 0.47,
        "stl": 0.14,
        "blk": 0.41,
        "turnover": 0.59,
        "pf": 1.35,
        "pts": 4.73,
        "fg_pct": 0.551,
        "fg3_pct": 0.0,
        "ft_pct": 0.636
    },
    {
        "games_played": 3,
        "player_id": 1905,
        "season": 2016,
        "min": "12:51",
        "fgm": 0.67,
        "fga": 2.67,
        "fg3m": 0.33,
        "fg3a": 1.0,
        "ftm": 0.67,
        "fta": 1.0,
        "oreb": 0.0,
        "dreb": 0.67,
        "reb": 0.67,
        "ast": 1.67,
        "stl": 0.33,
        "blk": 0.33,
        "turnover": 0.33,
        "pf": 2.0,
        "pts": 2.33,
        "fg_pct": 0.25,
        "fg3_pct": 0.333,
        "ft_pct": 0.667
    },
    {
        "games_played": 8,
        "player_id": 1906,
        "season": 2016,
        "min": "9:29",
        "fgm": 1.75,
        "fga": 3.88,
        "fg3m": 0.25,
        "fg3a": 0.75,
        "ftm": 1.13,
        "fta": 1.38,
        "oreb": 1.0,
        "dreb": 1.75,
        "reb": 2.75,
        "ast": 0.5,
        "stl": 0.13,
        "blk": 0.13,
        "turnover": 0.75,
        "pf": 1.0,
        "pts": 4.88,
        "fg_pct": 0.452,
        "fg3_pct": 0.333,
        "ft_pct": 0.818
    },
    {
        "games_played": 3,
        "player_id": 1923,
        "season": 2016,
        "min": "10:26",
        "fgm": 1.67,
        "fga": 4.0,
        "fg3m": 0.67,
        "fg3a": 2.33,
        "ftm": 0.0,
        "fta": 0.0,
        "oreb": 0.67,
        "dreb": 1.0,
        "reb": 1.67,
        "ast": 0.67,
        "stl": 0.0,
        "blk": 0.0,
        "turnover": 1.33,
        "pf": 0.67,
        "pts": 4.0,
        "fg_pct": 0.417,
        "fg3_pct": 0.286,
        "ft_pct": 0
    },
    {
        "games_played": 13,
        "player_id": 1933,
        "season": 2016,
        "min": "9:36",
        "fgm": 1.23,
        "fga": 4.0,
        "fg3m": 0.23,
        "fg3a": 1.0,
        "ftm": 0.62,
        "fta": 0.77,
        "oreb": 0.0,
        "dreb": 0.85,
        "reb": 0.85,
        "ast": 1.08,
        "stl": 0.62,
        "blk": 0.0,
        "turnover": 0.54,
        "pf": 1.38,
        "pts": 3.31,
        "fg_pct": 0.308,
        "fg3_pct": 0.231,
        "ft_pct": 0.8
    },
    {
        "games_played": 50,
        "player_id": 1941,
        "season": 2016,
        "min": "16:05",
        "fgm": 2.16,
        "fga": 4.88,
        "fg3m": 0.6,
        "fg3a": 1.94,
        "ftm": 1.16,
        "fta": 1.78,
        "oreb": 0.38,
        "dreb": 2.22,
        "reb": 2.6,
        "ast": 0.56,
        "stl": 0.28,
        "blk": 0.14,
        "turnover": 0.56,
        "pf": 1.2,
        "pts": 6.08,
        "fg_pct": 0.443,
        "fg3_pct": 0.309,
        "ft_pct": 0.652
    },
    {
        "games_played": 61,
        "player_id": 1959,
        "season": 2016,
        "min": "14:17",
        "fgm": 1.26,
        "fga": 2.75,
        "fg3m": 0.0,
        "fg3a": 0.02,
        "ftm": 0.38,
        "fta": 0.54,
        "oreb": 1.72,
        "dreb": 1.87,
        "reb": 3.59,
        "ast": 0.93,
        "stl": 0.3,
        "blk": 0.39,
        "turnover": 0.48,
        "pf": 1.28,
        "pts": 2.9,
        "fg_pct": 0.458,
        "fg3_pct": 0.0,
        "ft_pct": 0.697
    },
    {
        "games_played": 62,
        "player_id": 1966,
        "season": 2016,
        "min": "12:31",
        "fgm": 0.89,
        "fga": 2.29,
        "fg3m": 0.27,
        "fg3a": 0.74,
        "ftm": 0.4,
        "fta": 0.65,
        "oreb": 0.32,
        "dreb": 1.42,
        "reb": 1.74,
        "ast": 0.87,
        "stl": 0.76,
        "blk": 0.23,
        "turnover": 0.68,
        "pf": 1.31,
        "pts": 2.45,
        "fg_pct": 0.387,
        "fg3_pct": 0.37,
        "ft_pct": 0.625
    },
    {
        "games_played": 11,
        "player_id": 1978,
        "season": 2016,
        "min": "10:42",
        "fgm": 1.36,
        "fga": 4.27,
        "fg3m": 0.27,
        "fg3a": 1.64,
        "ftm": 0.36,
        "fta": 0.73,
        "oreb": 0.91,
        "dreb": 1.55,
        "reb": 2.45,
        "ast": 0.27,
        "stl": 0.36,
        "blk": 0.09,
        "turnover": 0.36,
        "pf": 1.55,
        "pts": 3.36,
        "fg_pct": 0.319,
        "fg3_pct": 0.167,
        "ft_pct": 0.5
    },
    {
        "games_played": 51,
        "player_id": 1983,
        "season": 2016,
        "min": "10:17",
        "fgm": 1.53,
        "fga": 3.1,
        "fg3m": 0.0,
        "fg3a": 0.02,
        "ftm": 0.43,
        "fta": 0.76,
        "oreb": 0.84,
        "dreb": 1.59,
        "reb": 2.43,
        "ast": 0.82,
        "stl": 0.14,
        "blk": 0.41,
        "turnover": 0.39,
        "pf": 1.2,
        "pts": 3.49,
        "fg_pct": 0.494,
        "fg3_pct": 0.0,
        "ft_pct": 0.564
    },
    {
        "games_played": 54,
        "player_id": 1987,
        "season": 2016,
        "min": "23:32",
        "fgm": 4.28,
        "fga": 9.11,
        "fg3m": 0.35,
        "fg3a": 1.39,
        "ftm": 1.91,
        "fta": 3.15,
        "oreb": 1.2,
        "dreb": 4.46,
        "reb": 5.67,
        "ast": 1.09,
        "stl": 0.74,
        "blk": 1.0,
        "turnover": 0.89,
        "pf": 1.24,
        "pts": 10.81,
        "fg_pct": 0.47,
        "fg3_pct": 0.253,
        "ft_pct": 0.606
    },
    {
        "games_played": 34,
        "player_id": 1988,
        "season": 2016,
        "min": "14:04",
        "fgm": 1.68,
        "fga": 4.06,
        "fg3m": 0.32,
        "fg3a": 1.38,
        "ftm": 0.74,
        "fta": 1.44,
        "oreb": 0.76,
        "dreb": 2.21,
        "reb": 2.97,
        "ast": 0.94,
        "stl": 0.53,
        "blk": 0.32,
        "turnover": 0.91,
        "pf": 1.62,
        "pts": 4.41,
        "fg_pct": 0.413,
        "fg3_pct": 0.234,
        "ft_pct": 0.51
    },
    {
        "games_played": 32,
        "player_id": 1991,
        "season": 2016,
        "min": "12:02",
        "fgm": 1.06,
        "fga": 2.59,
        "fg3m": 0.22,
        "fg3a": 1.16,
        "ftm": 0.41,
        "fta": 0.53,
        "oreb": 0.25,
        "dreb": 1.25,
        "reb": 1.5,
        "ast": 0.28,
        "stl": 0.22,
        "blk": 0.16,
        "turnover": 0.34,
        "pf": 0.91,
        "pts": 2.75,
        "fg_pct": 0.41,
        "fg3_pct": 0.189,
        "ft_pct": 0.765
    },
    {
        "games_played": 41,
        "player_id": 1993,
        "season": 2016,
        "min": "10:09",
        "fgm": 1.12,
        "fga": 2.98,
        "fg3m": 0.41,
        "fg3a": 1.07,
        "ftm": 0.8,
        "fta": 0.95,
        "oreb": 0.12,
        "dreb": 0.83,
        "reb": 0.95,
        "ast": 1.27,
        "stl": 0.22,
        "blk": 0.02,
        "turnover": 0.63,
        "pf": 0.44,
        "pts": 3.46,
        "fg_pct": 0.377,
        "fg3_pct": 0.386,
        "ft_pct": 0.846
    },
    {
        "games_played": 48,
        "player_id": 1996,
        "season": 2016,
        "min": "11:40",
        "fgm": 2.19,
        "fga": 4.08,
        "fg3m": 0.0,
        "fg3a": 0.02,
        "ftm": 0.65,
        "fta": 1.38,
        "oreb": 1.75,
        "dreb": 2.9,
        "reb": 4.65,
        "ast": 0.65,
        "stl": 0.54,
        "blk": 0.19,
        "turnover": 0.96,
        "pf": 1.58,
        "pts": 5.02,
        "fg_pct": 0.536,
        "fg3_pct": 0.0,
        "ft_pct": 0.47
    }
]